CHANGELOG
LICENSE
MANIFEST.in
README.rst
requirements.txt
setup.py
django_happystamp.egg-info/PKG-INFO
django_happystamp.egg-info/SOURCES.txt
django_happystamp.egg-info/dependency_links.txt
django_happystamp.egg-info/requires.txt
django_happystamp.egg-info/top_level.txt
happystamp/__init__.py
happystamp/admin.py
happystamp/gcm.py
happystamp/middleware.py
happystamp/models.py
happystamp/permissions.py
happystamp/serializers.py
happystamp/urls.py
happystamp/util.py
happystamp/views.py
happystamp/static/css/admin/mcard.css
happystamp/static/css/admin/mmerchant.css
happystamp/static/css/admin/mprogram.css
happystamp/static/css/customer/style.css
happystamp/static/fonts/Lato-Black.ttf
happystamp/static/fonts/Lato-BlackItalic.ttf
happystamp/static/fonts/Lato-Bold.ttf
happystamp/static/fonts/Lato-BoldItalic.ttf
happystamp/static/fonts/Lato-Hairline.ttf
happystamp/static/fonts/Lato-HairlineItalic.ttf
happystamp/static/fonts/Lato-Heavy.ttf
happystamp/static/fonts/Lato-HeavyItalic.ttf
happystamp/static/fonts/Lato-Italic.ttf
happystamp/static/fonts/Lato-Light.ttf
happystamp/static/fonts/Lato-LightItalic.ttf
happystamp/static/fonts/Lato-Medium.ttf
happystamp/static/fonts/Lato-MediumItalic.ttf
happystamp/static/fonts/Lato-Regular.ttf
happystamp/static/fonts/Lato-Semibold.ttf
happystamp/static/fonts/Lato-SemiboldItalic.ttf
happystamp/static/fonts/Lato-Thin.ttf
happystamp/static/fonts/Lato-ThinItalic.ttf
happystamp/static/fonts/README.txt
happystamp/static/img/app_sticker.png
happystamp/static/img/card_details.png
happystamp/static/img/card_list.png
happystamp/static/img/portal.logo.png
happystamp/static/img/redeem_card.png
happystamp/static/img/reward_card.png
happystamp/templates/admin/happystamp/mcard/change_form.html
happystamp/templates/admin/happystamp/mprogram/change_form.html
happystamp/templates/admin/happystamp/mprogram/preview_form.html
happystamp/templates/admin/happystamp/mprogram/qrcodes_form.html
happystamp/templates/customer/notifications.html
happystamp/templates/includes/daily_metrics.html
happystamp/templatetags/happystamp_tags.py
happystamp/templatetags/__pycache__/happystamp_tags.cpython-34.pyc